setup.py
movie_rec_marking/__init__.py
movie_rec_marking/test_milestone_1.py
movie_rec_marking/test_milestone_2.py
movie_rec_marking/test_milestone_3.py
movie_rec_marking/test_milestone_4.py
movie_rec_marking/test_milestone_5.py
movie_rec_marking_aicore.egg-info/PKG-INFO
movie_rec_marking_aicore.egg-info/SOURCES.txt
movie_rec_marking_aicore.egg-info/dependency_links.txt
movie_rec_marking_aicore.egg-info/requires.txt
movie_rec_marking_aicore.egg-info/top_level.txt