Metadata-Version: 2.1
Name: movie-rec-marking-aicore
Version: 0.1.3
Summary: An automated marking system for the movie recommendation project
Author: Ivan Ying
Author-email: ivan@theaicore.com
Requires-Python: >=3.6
